bw_matchbox/VERSION
bw_matchbox/__init__.py
bw_matchbox/comments.py
bw_matchbox/datapackages.py
bw_matchbox/export.py
bw_matchbox/matching.py
bw_matchbox/scores.py
bw_matchbox/utils.py
bw_matchbox/webapp.py
bw_matchbox/assets/css/allocate-page-allocate-mode.css
bw_matchbox/assets/css/allocate-page-groups.css
bw_matchbox/assets/css/allocate-page-inputs-table.css
bw_matchbox/assets/css/allocate-page-toolbar.css
bw_matchbox/assets/css/allocate-page.css
bw_matchbox/assets/css/comments-filters.css
bw_matchbox/assets/css/comments.css
bw_matchbox/assets/css/common-indicators.css
bw_matchbox/assets/css/common-modal.css
bw_matchbox/assets/css/common-notify.css
bw_matchbox/assets/css/common-page-header.css
bw_matchbox/assets/css/common.css
bw_matchbox/assets/css/compare.css
bw_matchbox/assets/css/customizations.css
bw_matchbox/assets/css/fixed-table.css
bw_matchbox/assets/css/match.css
bw_matchbox/assets/css/normalize.css
bw_matchbox/assets/css/panels-layout.css
bw_matchbox/assets/css/process-detail.css
bw_matchbox/assets/css/processes-list.css
bw_matchbox/assets/css/recent-processes.css
bw_matchbox/assets/css/scores-list.css
bw_matchbox/assets/css/skeleton.css
bw_matchbox/assets/css/thread-comments-threads-list.css
bw_matchbox/assets/css/thread-comments.css
bw_matchbox/assets/css/tooltip.css
bw_matchbox/assets/images/csv.svg
bw_matchbox/assets/images/favicon.ico
bw_matchbox/assets/images/json.svg
bw_matchbox/assets/images/xml.svg
bw_matchbox/assets/modules/@types/TComment.d.ts
bw_matchbox/assets/modules/@types/TDataRecord.d.ts
bw_matchbox/assets/modules/@types/TErrorLike.d.ts
bw_matchbox/assets/modules/@types/TEvents.d.ts
bw_matchbox/assets/modules/@types/THtmlContent.d.ts
bw_matchbox/assets/modules/@types/TProcess.d.ts
bw_matchbox/assets/modules/@types/TRecentProcesses.d.ts
bw_matchbox/assets/modules/@types/TSetTimeout.d.ts
bw_matchbox/assets/modules/@types/TSharedHandlers.d.ts
bw_matchbox/assets/modules/@types/TUser.d.ts
bw_matchbox/assets/modules/@types/TUserRole.d.ts
bw_matchbox-2.6.dist-info/LICENSE
bw_matchbox-2.6.dist-info/METADATA
bw_matchbox-2.6.dist-info/WHEEL
bw_matchbox-2.6.dist-info/entry_points.txt
bw_matchbox-2.6.dist-info/top_level.txt
bw_matchbox-2.6.dist-info/RECORD
