Metadata-Version: 2.1
Name: bw-matchbox
Version: 2.6
Summary: Browser to match Brightway databases
Home-page: https://github.com/cauldron/bw_matchbox
Author: Chris Mutel
Author-email: <cmutel@gmail.com>
Maintainer: Chris Mutel
Maintainer-email: <cmutel@gmail.com>
License: MIT
Project-URL: source, https://github.com/cauldron/bw_matchbox
Project-URL: homepage, https://github.com/cauldron/bw_matchbox
Project-URL: tracker, https://github.com/cauldron/bw_matchbox/issues
Keywords: "brightway","development"
Platform: any
Classifier: Development Status :: 4 - Beta
Classifier: Programming Language :: Python
Classifier: Programming Language :: Python :: 3
Classifier: Programming Language :: Python :: 3.8
Classifier: Programming Language :: Python :: 3.9
Classifier: Programming Language :: Python :: 3.10
Classifier: Programming Language :: Python :: 3.11
Requires-Python: >=3.8
License-File: LICENSE
Requires-Dist: brightway25
Requires-Dist: docopt-ng
Requires-Dist: docopt
Requires-Dist: flask
Requires-Dist: flask-httpauth
Requires-Dist: levenshtein
Requires-Dist: tomli
Requires-Dist: werkzeug
Provides-Extra: dev
Requires-Dist: pre-commit ; extra == 'dev'
Requires-Dist: pylint ; extra == 'dev'
Provides-Extra: docs
Requires-Dist: sphinx ; extra == 'docs'
Requires-Dist: myst-parser ; extra == 'docs'
Requires-Dist: furo ; extra == 'docs'
Provides-Extra: testing
Requires-Dist: setuptools ; extra == 'testing'
Requires-Dist: pytest ; extra == 'testing'
Requires-Dist: pytest-cov ; extra == 'testing'
